AUTHORS.rst
CONTRIBUTING.rst
HISTORY.rst
LICENSE
MANIFEST.in
README.rst
setup.cfg
setup.py
docs/Makefile
docs/authors.rst
docs/conf.py
docs/contributing.rst
docs/history.rst
docs/index.rst
docs/installation.rst
docs/make.bat
docs/readme.rst
docs/usage.rst
hotsyk/__init__.py
hotsyk/hotsyk.py
hotsyk.egg-info/PKG-INFO
hotsyk.egg-info/SOURCES.txt
hotsyk.egg-info/dependency_links.txt
hotsyk.egg-info/not-zip-safe
hotsyk.egg-info/top_level.txt
tests/__init__.py
tests/test_hotsyk.py