Metadata-Version: 1.1
Name: hotsyk
Version: 0.1.1
Summary: Volodymyr Hotsyk's CV
Home-page: https://github.com/hotsyk/hotsyk
Author: Volodymyr Hotsyk
Author-email: hotsyk@hotsyk.com
License: BSD
Keywords: hotsyk
Platform: UNKNOWN
Classifier: Development Status :: 2 - Pre-Alpha
Classifier: Intended Audience :: Developers
Classifier: License :: OSI Approved :: BSD License
Classifier: Natural Language :: English
Classifier: Programming Language :: Python :: 2
Classifier: Programming Language :: Python :: 2.6
Classifier: Programming Language :: Python :: 2.7
Classifier: Programming Language :: Python :: 3
Classifier: Programming Language :: Python :: 3.3
Classifier: Programming Language :: Python :: 3.4
